kimbo/__init__.py
kimbo/mixins/__init__.py
kimbo/mixins/api_gateway.py
kimbo/mixins/sqs.py
kimbo-0.1.1.dist-info/LICENSE
kimbo-0.1.1.dist-info/METADATA
kimbo-0.1.1.dist-info/WHEEL
kimbo-0.1.1.dist-info/top_level.txt
kimbo-0.1.1.dist-info/RECORD
