Metadata-Version: 2.1
Name: kimbo
Version: 0.1.1
Summary: A Python micro framework for AWS lambda inspired by mixin design pattern.
Author: NiumXp
License: MIT
Project-URL: Homepage, https://github.com/NiumXp/kimbo
Project-URL: Bug Tracker, https://github.com/NiumXp/kimbo/issues
Classifier: Development Status :: 5 - Production/Stable
Classifier: Operating System :: OS Independent
Classifier: Programming Language :: Python :: 3.6
Classifier: Programming Language :: Python :: 3.7
Classifier: Programming Language :: Python :: 3.8
Classifier: Programming Language :: Python :: 3.9
Classifier: Programming Language :: Python :: 3.10
Classifier: Programming Language :: Python :: 3.11
Classifier: Topic :: Utilities
Requires-Python: >=3.6
License-File: LICENSE
